docudevs/__init__.py
docudevs/cli.py
docudevs/client.py
docudevs/docudevs_client.py
docudevs/errors.py
docudevs/py.typed
docudevs/types.py
docudevs/api/__init__.py
docudevs/api/azure_ocr_providers/__init__.py
docudevs/api/azure_ocr_providers/create_ocr_provider.py
docudevs/api/azure_ocr_providers/delete_ocr_provider.py
docudevs/api/azure_ocr_providers/get_ocr_provider.py
docudevs/api/azure_ocr_providers/list_ocr_keys.py
docudevs/api/azure_ocr_providers/list_ocr_providers.py
docudevs/api/azure_ocr_providers/update_ocr_key.py
docudevs/api/azure_ocr_providers/update_ocr_provider.py
docudevs/api/batch/__init__.py
docudevs/api/batch/create_batch.py
docudevs/api/batch/process_batch.py
docudevs/api/batch/schedule_batch.py
docudevs/api/batch/upload_batch_document.py
docudevs/api/cases/__init__.py
docudevs/api/cases/create_case.py
docudevs/api/cases/delete_case.py
docudevs/api/cases/delete_case_document.py
docudevs/api/cases/get_case.py
docudevs/api/cases/get_case_document.py
docudevs/api/cases/list_case_documents.py
docudevs/api/cases/list_cases.py
docudevs/api/cases/update_case.py
docudevs/api/cases/upload_case_document.py
docudevs/api/cases/upload_case_document_legacy.py
docudevs/api/configuration/__init__.py
docudevs/api/configuration/delete_configuration.py
docudevs/api/configuration/get_configuration.py
docudevs/api/configuration/list_configurations.py
docudevs/api/configuration/save_configuration.py
docudevs/api/default/__init__.py
docudevs/api/default/get_current_user.py
docudevs/api/default/resolve_ocr_provider.py
docudevs/api/document/__init__.py
docudevs/api/document/generate_schema.py
docudevs/api/document/ocr_document.py
docudevs/api/document/ocr_document_sync.py
docudevs/api/document/process_document.py
docudevs/api/document/process_document_with_configuration.py
docudevs/api/document/upload_document.py
docudevs/api/document/upload_files.py
docudevs/api/document/upload_files_sync.py
docudevs/api/document/upload_template.py
docudevs/api/internal_llm/__init__.py
docu_devs_api_client-1.4.8.dist-info/METADATA
docu_devs_api_client-1.4.8.dist-info/WHEEL
docu_devs_api_client-1.4.8.dist-info/entry_points.txt
docu_devs_api_client-1.4.8.dist-info/RECORD
