Metadata-Version: 2.4
Name: docu-devs-api-client
Version: 1.4.8
Summary: A client library for accessing DocuDevs API
Project-URL: Homepage, https://www.docudevs.ai/
Project-URL: Repository, https://github.com/piizei/docudevs.git
Project-URL: Documentation, https://docs.docudevs.ai
Author: pj@docudevs.ai
Keywords: ai document processing,docudevs client,document processing,document to data,ocr
Classifier: Development Status :: 4 - Beta
Classifier: Intended Audience :: Developers
Classifier: License :: OSI Approved :: MIT License
Classifier: Programming Language :: Python :: 3
Classifier: Programming Language :: Python :: 3.9
Classifier: Programming Language :: Python :: 3.10
Classifier: Programming Language :: Python :: 3.11
Classifier: Programming Language :: Python :: 3.12
Classifier: Programming Language :: Python :: 3.13
Requires-Python: <4.0,>=3.9
Requires-Dist: asyncio>=3.4.3
Requires-Dist: attrs>=21.3.0
Requires-Dist: click>=8.0.0
Requires-Dist: httpx<0.28.1,>=0.20.0
Requires-Dist: pydantic>=2.0.0
Requires-Dist: python-dateutil>=2.8.0
Provides-Extra: dev
Requires-Dist: mypy>=1.15.0; extra == 'dev'
Requires-Dist: openapi-python-client>=0.24.2; extra == 'dev'
Requires-Dist: pytest-asyncio>=0.26.0; extra == 'dev'
Requires-Dist: pytest>=8.3.5; extra == 'dev'
Requires-Dist: ruff>=0.11.2; extra == 'dev'
